aw_core/__about__.py
aw_core/__init__.py
aw_core/config.py
aw_core/decorators.py
aw_core/dirs.py
aw_core/log.py
aw_core/models.py
aw_core/py.typed
aw_core/schema.py
aw_core/schemas/bucket.json
aw_core/schemas/event.json
aw_core/schemas/export.json
aw_core/util.py
aw_datastore/__init__.py
aw_datastore/benchmark.py
aw_datastore/datastore.py
aw_datastore/migration.py
aw_datastore/py.typed
aw_datastore/storages/__init__.py
aw_datastore/storages/abstract.py
aw_datastore/storages/memory.py
aw_datastore/storages/peewee.py
aw_datastore/storages/sqlite.py
aw_query/__init__.py
aw_query/exceptions.py
aw_query/functions.py
aw_query/py.typed
aw_query/query2.py
aw_transform/__init__.py
aw_transform/chunk_events_by_key.py
aw_transform/classify.py
aw_transform/filter_keyvals.py
aw_transform/filter_period_intersect.py
aw_transform/flood.py
aw_transform/heartbeats.py
aw_transform/merge_events_by_keys.py
aw_transform/py.typed
aw_transform/simplify.py
aw_transform/sort_by.py
aw_transform/split_url_events.py
aw_transform/union_no_overlap.py
aw_core-0.5.17.dist-info/LICENSE.txt
aw_core-0.5.17.dist-info/METADATA
aw_core-0.5.17.dist-info/WHEEL
aw_core-0.5.17.dist-info/entry_points.txt
aw_core-0.5.17.dist-info/RECORD
