Metadata-Version: 2.1
Name: aw-core
Version: 0.5.17
Summary: Core library for ActivityWatch
Home-page: https://activitywatch.net/
License: MPL-2.0
Author: Erik Bjäreholt
Author-email: erik@bjareho.lt
Requires-Python: >=3.8,<4.0
Classifier: License :: OSI Approved
Classifier: Programming Language :: Python :: 3
Classifier: Programming Language :: Python :: 3.8
Classifier: Programming Language :: Python :: 3.9
Classifier: Programming Language :: Python :: 3.10
Classifier: Programming Language :: Python :: 3.11
Classifier: Programming Language :: Python :: 3.12
Requires-Dist: deprecation
Requires-Dist: iso8601
Requires-Dist: jsonschema (>=4.3,<5.0)
Requires-Dist: peewee (==3.*)
Requires-Dist: platformdirs (==3.10)
Requires-Dist: rfc3339-validator (>=0.1.4,<0.2.0)
Requires-Dist: strict-rfc3339 (>=0.7,<0.8)
Requires-Dist: timeslot
Requires-Dist: tomlkit
Project-URL: Documentation, https://docs.activitywatch.net/
Project-URL: Repository, https://github.com/ActivityWatch/aw-core/
